Workbook

Sheet Assumption Sheet
A1: Total Project Cost
A2: Particulars | B2: Total Cost | C2: Margin Requirement | D2: Promoter's Contribution | E2: Bank Finance
B3: Amount in Rs. in Crores / Proportion in %age
A4: Cost of Land [already acquired by the Company] | B4: 20 | C4: 1 | D4: =B4*C4 -> 20 | E4: =B4-D4 -> 0
A5: Cost of Approvals / Premiums & Regulatory Costs | B5: 10 | C5: 0.5 | D5: =B5*C5 -> 5 | E5: =B5-D5 -> 5
A6: Cost of Construction of the Hotel Building | B6: 40 | C6: 0.3 | D6: =B6*C6 -> 12 | E6: =B6-D6 -> 28
A7: Cost of Interiors & Kitchen Equipments | B7: 50 | C7: 0.25 | D7: =B7*C7 -> 12.5 | E7: =B7-D7 -> 37.5
A8: Contingency Margin | B8: 7.5 | C8: 1 | D8: =B8*C8 -> 7.5 | E8: =B8-D8 -> 0
A9: Core Project Cost [A] | B9: =SUM(B4:B8) -> 127.5 | D9: =SUM(D4:D8) -> 57 | E9: =SUM(E4:E8) -> 70.5
A10: Interest During Construction [B] | B10: =J73 -> 7.0775 | C10: 1 | D10: =B10*C10 -> 7.0775 | E10: =B10-D10 -> 0
A11: Total Project Cost [A+B] | B11: =SUM(B9:B10) -> 134.5775 | D11: =SUM(D9:D10) -> 64.0775 | E11: =SUM(E9:E10) -> 70.5
A14: Cost Phasing in %age
A15: Particulars | B15: 2024-25 | F15: 2025-26 | J15: Total
B16: Q I | C16: Q II | D16: Q III | E16: Q IV | F16: Q I | G16: Q II | H16: Q III | I16: Q IV
A17: Cost of Land [already acquired by the Company] | B17: 1 | C17: 0 | D17: 0 | E17: 0 | F17: 0 | G17: 0 | H17: 0 | I17: =J17-SUM(B17:H17) -> 0 | J17: 1
A18: Cost of Approvals / Premiums & Regulatory Costs | B18: 0.25 | C18: 0.5 | D18: 0.1 | E18: 0 | F18: 0 | G18: 0 | H18: 0.1 | I18: =J18-SUM(B18:H18) -> 0.05 | J18: 1
A19: Cost of Construction of the Hotel Building | B19: 0.1 | C19: 0.2 | D19: 0.3 | E19: 0.35 | F19: 0.05 | G19: 0 | H19: 0 | I19: =J19-SUM(B19:H19) -> 0 | J19: 1
A20: Cost of Interiors & Kitchen Equipments | B20: 0 | C20: 0 | D20: 0.1 | E20: 0.1 | F20: 0.2 | G20: 0.2 | H20: 0.3 | I20: =J20-SUM(B20:H20) -> 0.1 | J20: 1
A21: Contingency Margin | B21: 0 | C21: 0 | D21: 0 | E21: 0 | F21: 0 | G21: 0 | H21: 0.5 | I21: =J21-SUM(B21:H21) -> 0.5 | J21: 1
A23: Cost Incurred in Rs.
A24: Particulars | B24: 2024-25 | F24: 2025-26 | J24: Total
B25: Q I | C25: Q II | D25: Q III | E25: Q IV | F25: Q I | G25: Q II | H25: Q III | I25: Q IV
A26: Cost of Land [already acquired by the Company] | B26: =$B$4*B17 -> 20 | C26: =$B$4*C17 -> 0 | D26: =$B$4*D17 -> 0 | E26: =$B$4*E17 -> 0 | F26: =$B$4*F17 -> 0 | G26: =$B$4*G17 -> 0 | H26: =$B$4*H17 -> 0 | I26: =$B$4*I17 -> 0 | J26: =SUM(B26:I26) -> 20
A27: Cost of Approvals / Premiums & Regulatory Costs | B27: =$B$5*B18 -> 2.5 | C27: =$B$5*C18 -> 5 | D27: =$B$5*D18 -> 1 | E27: =$B$5*E18 -> 0 | F27: =$B$5*F18 -> 0 | G27: =$B$5*G18 -> 0 | H27: =$B$5*H18 -> 1 | I27: =$B$5*I18 -> 0.5 | J27: =SUM(B27:I27) -> 10
A28: Cost of Construction of the Hotel Building | B28: =$B$6*B19 -> 4 | C28: =$B$6*C19 -> 8 | D28: =$B$6*D19 -> 12 | E28: =$B$6*E19 -> 14 | F28: =$B$6*F19 -> 2 | G28: =$B$6*G19 -> 0 | H28: =$B$6*H19 -> 0 | I28: =$B$6*I19 -> 0 | J28: =SUM(B28:I28) -> 40
A29: Cost of Interiors & Kitchen Equipments | B29: =$B$7*B20 -> 0 | C29: =$B$7*C20 -> 0 | D29: =$B$7*D20 -> 5 | E29: =$B$7*E20 -> 5 | F29: =$B$7*F20 -> 10 | G29: =$B$7*G20 -> 10 | H29: =$B$7*H20 -> 15 | I29: =$B$7*I20 -> 5 | J29: =SUM(B29:I29) -> 50
A30: Contingency Margin | B30: =$B$8*B21 -> 0 | C30: =$B$8*C21 -> 0 | D30: =$B$8*D21 -> 0 | E30: =$B$8*E21 -> 0 | F30: =$B$8*F21 -> 0 | G30: =$B$8*G21 -> 0 | H30: =$B$8*H21 -> 3.75 | I30: =$B$8*I21 -> 3.75 | J30: =SUM(B30:I30) -> 7.5
A31: Total Cost Incurred | B31: =SUM(B26:B30) -> 26.5 | C31: =SUM(C26:C30) -> 13 | D31: =SUM(D26:D30) -> 18 | E31: =SUM(E26:E30) -> 19 | F31: =SUM(F26:F30) -> 12 | G31: =SUM(G26:G30) -> 10 | H31: =SUM(H26:H30) -> 19.75 | I31: =SUM(I26:I30) -> 9.25 | J31: =SUM(J26:J30) -> 127.5
A34: Term Loan Draw-Down & Promoters Margin requriement
A36: Particulars | B36: 2024-25 | F36: 2025-26 | J36: Total
B37: Q I | C37: Q II | D37: Q III | E37: Q IV | F37: Q I | G37: Q II | H37: Q III | I37: Q IV
A38: Cost of Land [already acquired by the Company]
A39: Promoter's Funding | B39: =B41*$C$4 -> 20 | C39: =C41*$C$4 -> 0 | D39: =D41*$C$4 -> 0 | E39: =E41*$C$4 -> 0 | F39: =F41*$C$4 -> 0 | G39: =G41*$C$4 -> 0 | H39: =H41*$C$4 -> 0 | I39: =I41*$C$4 -> 0 | J39: =SUM(B39:I39) -> 20
A40: Bank Finance | B40: =B41-B39 -> 0 | C40: =C41-C39 -> 0 | D40: =D41-D39 -> 0 | E40: =E41-E39 -> 0 | F40: =F41-F39 -> 0 | G40: =G41-G39 -> 0 | H40: =H41-H39 -> 0 | I40: =I41-I39 -> 0 | J40: =SUM(B40:I40) -> 0
A41: Total Cost of Land | B41: =B26 -> 20 | C41: =C26 -> 0 | D41: =D26 -> 0 | E41: =E26 -> 0 | F41: =F26 -> 0 | G41: =G26 -> 0 | H41: =H26 -> 0 | I41: =I26 -> 0 | J41: =SUM(B41:I41) -> 20
A43: Cost of Approvals / Premiums & Regulatory Costs
A44: Promoter's Funding | B44: =B46*$C$5 -> 1.25 | C44: =C46*$C$5 -> 2.5 | D44: =D46*$C$5 -> 0.5 | E44: =E46*$C$5 -> 0 | F44: =F46*$C$5 -> 0 | G44: =G46*$C$5 -> 0 | H44: =H46*$C$5 -> 0.5 | I44: =I46*$C$5 -> 0.25 | J44: =SUM(B44:I44) -> 5
A45: Bank Finance | B45: =B46-B44 -> 1.25 | C45: =C46-C44 -> 2.5 | D45: =D46-D44 -> 0.5 | E45: =E46-E44 -> 0 | F45: =F46-F44 -> 0 | G45: =G46-G44 -> 0 | H45: =H46-H44 -> 0.5 | I45: =I46-I44 -> 0.25 | J45: =SUM(B45:I45) -> 5
A46: Total Cost of Approvals / Premiums & Regulatory Costs | B46: =B27 -> 2.5 | C46: =C27 -> 5 | D46: =D27 -> 1 | E46: =E27 -> 0 | F46: =F27 -> 0 | G46: =G27 -> 0 | H46: =H27 -> 1 | I46: =I27 -> 0.5 | J46: =SUM(B46:I46) -> 10
A48: Cost of Construction of the Hotel Building
A49: Promoter's Funding | B49: =B51*$C$6 -> 1.2 | C49: =C51*$C$6 -> 2.4 | D49: =D51*$C$6 -> 3.6 | E49: =E51*$C$6 -> 4.2 | F49: =F51*$C$6 -> 0.6 | G49: =G51*$C$6 -> 0 | H49: =H51*$C$6 -> 0 | I49: =I51*$C$6 -> 0 | J49: =SUM(B49:I49) -> 12
A50: Bank Finance | B50: =B51-B49 -> 2.8 | C50: =C51-C49 -> 5.6 | D50: =D51-D49 -> 8.4 | E50: =E51-E49 -> 9.8 | F50: =F51-F49 -> 1.4 | G50: =G51-G49 -> 0 | H50: =H51-H49 -> 0 | I50: =I51-I49 -> 0 | J50: =SUM(B50:I50) -> 28
A51: Total Cost of Construction of the Hotel Building | B51: =B28 -> 4 | C51: =C28 -> 8 | D51: =D28 -> 12 | E51: =E28 -> 14 | F51: =F28 -> 2 | G51: =G28 -> 0 | H51: =H28 -> 0 | I51: =I28 -> 0 | J51: =SUM(B51:I51) -> 40
A53: Cost of Interiors & Kitchen Equipments
A54: Promoter's Funding | B54: =B56*$C$7 -> 0 | C54: =C56*$C$7 -> 0 | D54: =D56*$C$7 -> 1.25 | E54: =E56*$C$7 -> 1.25 | F54: =F56*$C$7 -> 2.5 | G54: =G56*$C$7 -> 2.5 | H54: =H56*$C$7 -> 3.75 | I54: =I56*$C$7 -> 1.25 | J54: =SUM(B54:I54) -> 12.5
A55: Bank Finance | B55: =B56-B54 -> 0 | C55: =C56-C54 -> 0 | D55: =D56-D54 -> 3.75 | E55: =E56-E54 -> 3.75 | F55: =F56-F54 -> 7.5 | G55: =G56-G54 -> 7.5 | H55: =H56-H54 -> 11.25 | I55: =I56-I54 -> 3.75 | J55: =SUM(B55:I55) -> 37.5
A56: Total Cost of Interiors & Kitchen Equipments | B56: =B29 -> 0 | C56: =C29 -> 0 | D56: =D29 -> 5 | E56: =E29 -> 5 | F56: =F29 -> 10 | G56: =G29 -> 10 | H56: =H29 -> 15 | I56: =I29 -> 5 | J56: =SUM(B56:I56) -> 50
A58: Contingency Margin
A59: Promoter's Funding | B59: =B61*$C$8 -> 0 | C59: =C61*$C$8 -> 0 | D59: =D61*$C$8 -> 0 | E59: =E61*$C$8 -> 0 | F59: =F61*$C$8 -> 0 | G59: =G61*$C$8 -> 0 | H59: =H61*$C$8 -> 3.75 | I59: =I61*$C$8 -> 3.75 | J59: =SUM(B59:I59) -> 7.5
A60: Bank Finance | B60: =B61-B59 -> 0 | C60: =C61-C59 -> 0 | D60: =D61-D59 -> 0 | E60: =E61-E59 -> 0 | F60: =F61-F59 -> 0 | G60: =G61-G59 -> 0 | H60: =H61-H59 -> 0 | I60: =I61-I59 -> 0 | J60: =SUM(B60:I60) -> 0
A61: Total Contingency Margin | B61: =B30 -> 0 | C61: =C30 -> 0 | D61: =D30 -> 0 | E61: =E30 -> 0 | F61: =F30 -> 0 | G61: =G30 -> 0 | H61: =H30 -> 3.75 | I61: =I30 -> 3.75 | J61: =SUM(B61:I61) -> 7.5
A63: Total Promoters Contribution | B63: =B39+B44+B49+B54+B59 -> 22.45 | C63: =C39+C44+C49+C54+C59 -> 4.9 | D63: =D39+D44+D49+D54+D59 -> 5.35 | E63: =E39+E44+E49+E54+E59 -> 5.45 | F63: =F39+F44+F49+F54+F59 -> 3.1 | G63: =G39+G44+G49+G54+G59 -> 2.5 | H63: =H39+H44+H49+H54+H59 -> 8 | I63: =I39+I44+I49+I54+I59 -> 5.25 | J63: =SUM(B63:I63) -> 57
A64: Total Bank Finance | B64: =B40+B45+B50+B55+B60 -> 4.05 | C64: =C40+C45+C50+C55+C60 -> 8.1 | D64: =D40+D45+D50+D55+D60 -> 12.65 | E64: =E40+E45+E50+E55+E60 -> 13.55 | F64: =F40+F45+F50+F55+F60 -> 8.9 | G64: =G40+G45+G50+G55+G60 -> 7.5 | H64: =H40+H45+H50+H55+H60 -> 11.75 | I64: =I40+I45+I50+I55+I60 -> 4 | J64: =SUM(B64:I64) -> 70.5
A65: Total Project Cost | B65: =SUM(B63:B64) -> 26.5 | C65: =SUM(C63:C64) -> 13 | D65: =SUM(D63:D64) -> 18 | E65: =SUM(E63:E64) -> 19 | F65: =SUM(F63:F64) -> 12 | G65: =SUM(G63:G64) -> 10 | H65: =SUM(H63:H64) -> 19.75 | I65: =SUM(I63:I64) -> 9.25 | J65: =SUM(J63:J64) -> 127.5
A67: Term Loan Draw-Down Schedule | B67: 2024-25 | F67: 2025-26 | J67: Total
B68: Q I | C68: Q II | D68: Q III | E68: Q IV | F68: Q I | G68: Q II | H68: Q III | I68: Q IV
A69: Opening Balance | B69: 0 | C69: =B71 -> 4.05 | D69: =C71 -> 12.15 | E69: =D71 -> 24.8 | F69: =E71 -> 38.35 | G69: =F71 -> 47.25 | H69: =G71 -> 54.75 | I69: =H71 -> 66.5 | J69: =B69 -> 0
A70: [+] Draw Down | B70: =B64 -> 4.05 | C70: =C64 -> 8.1 | D70: =D64 -> 12.65 | E70: =E64 -> 13.55 | F70: =F64 -> 8.9 | G70: =G64 -> 7.5 | H70: =H64 -> 11.75 | I70: =I64 -> 4 | J70: =SUM(B70:I70) -> 70.5
A71: Closing Balance | B71: =B69+B70 -> 4.05 | C71: =C69+C70 -> 12.15 | D71: =D69+D70 -> 24.8 | E71: =E69+E70 -> 38.35 | F71: =F69+F70 -> 47.25 | G71: =G69+G70 -> 54.75 | H71: =H69+H70 -> 66.5 | I71: =I69+I70 -> 70.5 | J71: =J69+J70 -> 70.5
A72: Average Balance | B72: =(B69+B71)/2 -> 2.025 | C72: =(C69+C71)/2 -> 8.1 | D72: =(D69+D71)/2 -> 18.475 | E72: =(E69+E71)/2 -> 31.575 | F72: =(F69+F71)/2 -> 42.8 | G72: =(G69+G71)/2 -> 51 | H72: =(H69+H71)/2 -> 60.625 | I72: =(I69+I71)/2 -> 68.5
A73: Interest During Construction | B73: =B72*$B$75*3/12 -> 0.050625 | C73: =C72*$B$75*3/12 -> 0.2025 | D73: =D72*$B$75*3/12 -> 0.461875 | E73: =E72*$B$75*3/12 -> 0.789375 | F73: =F72*$B$75*3/12 -> 1.07 | G73: =G72*$B$75*3/12 -> 1.275 | H73: =H72*$B$75*3/12 -> 1.515625 | I73: =I72*$B$75*3/12 -> 1.7125 | J73: =SUM(B73:I73) -> 7.0775
A75: Rate of Interest in Term Loan | B75: 0.1
A78: Name of the Main Item of the Project Cost | B78: Base Cost | C78: Cost of Approvals | D78: Contingency Margin | E78: IDC | F78: Total Cost
B79: All Amounts in Rs. in Crores
A80: Cost of Hotel Building | B80: =B6 -> 40 | C80: =B5 -> 10 | D80: =$B$8/2 -> 3.75 | E80: =$B$10/2 -> 3.53875 | F80: =SUM(B80:E80) -> 57.28875
A81: Cost of Kitchen Equipment & Machinery | B81: =B7 -> 50 | C81: =B5-C80 -> 0 | D81: =$B$8/2 -> 3.75 | E81: =$B$10/2 -> 3.53875 | F81: =SUM(B81:E81) -> 57.28875
A82: Total Cost | B82: =SUM(B80:B81) -> 90 | C82: =SUM(C80:C81) -> 10 | D82: =SUM(D80:D81) -> 7.5 | E82: =SUM(E80:E81) -> 7.0775 | F82: =SUM(F80:F81) -> 114.5775
A84: Useful Life Assumed for Charging Depreciation: | C84: Depreciation Per Year
A85: Factory Building | B85: 40 | C85: =F80/B85 -> 1.4322188
A86: Kitchen Equipment & Machinery | B86: 15 | C86: =F81/B86 -> 3.81925
C87: =SUM(C85:C86) -> 5.2514687
A89: Proportion in Revenue Stream:
A90: Room Revenue | B90: 0.55
A91: Food & Beverage | B91: 0.3
A92: Others | B92: =B93-SUM(B90:B91) -> 0.15
A93: Total | B93: 1
A95: Total Number of Rooms | B95: 125
A96: Number of Days in a Year for which the room may be offered | B96: 365
A97: Occupancy in %age | B97: 0.65
A98: Yearly Increase in Occupancy | B98: 0.025
A99: Tariff Charged per room per day | B99: 10000
A100: Annual Increase in Room Tariff | B100: 0.015
A104: Composition of Expenses:
A105: Food & Beverages Consumables | B105: 0.075
A106: Employee Costs | B106: 0.2
A107: Power & Fuel | B107: 0.06
A108: Other Variable Expenses | B108: 0.04
A109: Service Fees to Mariott [Room revenue] | B109: 0.05
A111: Fixed Expenses:
A112: Administrative & Selling Expenses | B112: 0.2
A113: Annual Increase | B113: 0.1
A115: Corporate Income tax | B115: 0.33
A118: Total Cash Out-Flow | B118: 2024-25 | C118: 2025-26 | D118: Total
A119: Total Cost incurred in Rs. in Crores | B119: =SUM(B31:E31) -> 76.5 | C119: =SUM(F31:I31) -> 51 | D119: =SUM(B119:C119) -> 127.5
A120: Interest During Construction in Rs. in Crores | B120: =SUM(B73:E73) -> 1.504375 | C120: =SUM(F73:I73) -> 5.573125 | D120: =SUM(B120:C120) -> 7.0775
A121: Total Cost incurred during the year in Rs. in Crores | B121: =SUM(B119:B120) -> 78.004375 | C121: =SUM(C119:C120) -> 56.573125 | D121: =SUM(D119:D120) -> 134.5775

Sheet Project Income Statement
A2: Particulars | B2: 2026-27 | C2: 2027-28 | D2: 2028-29 | E2: 2029-30 | F2: 2030-31 | G2: 2031-32 | H2: 2032-33 | I2: 2033-34 | J2: 2034-35 | K2: 2035-36
B3: All Amount in Rs. in Crores
A4: Occupancy Assumed | B4: ='Assumption Sheet'!B97 -> 0.65 | C4: =IF(B4+'Assumption Sheet'!$B$98>=80%,80%,'Project Income Statement'!B4+'Assumption Sheet'!$B$98) -> 0.675 | D4: =IF(C4+'Assumption Sheet'!$B$98>=80%,80%,'Project Income Statement'!C4+'Assumption Sheet'!$B$98) -> 0.7 | E4: =IF(D4+'Assumption Sheet'!$B$98>=80%,80%,'Project Income Statement'!D4+'Assumption Sheet'!$B$98) -> 0.725 | F4: =IF(E4+'Assumption Sheet'!$B$98>=80%,80%,'Project Income Statement'!E4+'Assumption Sheet'!$B$98) -> 0.75 | G4: =IF(F4+'Assumption Sheet'!$B$98>=80%,80%,'Project Income Statement'!F4+'Assumption Sheet'!$B$98) -> 0.775 | H4: =IF(G4+'Assumption Sheet'!$B$98>=80%,80%,'Project Income Statement'!G4+'Assumption Sheet'!$B$98) -> 0.8 | I4: =IF(H4+'Assumption Sheet'!$B$98>=80%,80%,'Project Income Statement'!H4+'Assumption Sheet'!$B$98) -> 0.8 | J4: =IF(I4+'Assumption Sheet'!$B$98>=80%,80%,'Project Income Statement'!I4+'Assumption Sheet'!$B$98) -> 0.8 | K4: =IF(J4+'Assumption Sheet'!$B$98>=80%,80%,'Project Income Statement'!J4+'Assumption Sheet'!$B$98) -> 0.8
A5: Room Tariff per day | B5: ='Assumption Sheet'!B99 -> 10000 | C5: =B5+(B5*'Assumption Sheet'!$B$100) -> 10150 | D5: =C5+(C5*'Assumption Sheet'!$B$100) -> 10302.25 | E5: =D5+(D5*'Assumption Sheet'!$B$100) -> 10456.784 | F5: =E5+(E5*'Assumption Sheet'!$B$100) -> 10613.636 | G5: =F5+(F5*'Assumption Sheet'!$B$100) -> 10772.84 | H5: =G5+(G5*'Assumption Sheet'!$B$100) -> 10934.433 | I5: =H5+(H5*'Assumption Sheet'!$B$100) -> 11098.449 | J5: =I5+(I5*'Assumption Sheet'!$B$100) -> 11264.926 | K5: =J5+(J5*'Assumption Sheet'!$B$100) -> 11433.9
A6: Total Revenues during the Year:
A7: Room revenues | B7: ='Assumption Sheet'!$B$95*'Assumption Sheet'!$B$96*'Project Income Statement'!B4*'Project Income Statement'!B5/10000000 -> 29.65625 | C7: ='Assumption Sheet'!$B$95*'Assumption Sheet'!$B$96*'Project Income Statement'!C4*'Project Income Statement'!C5/10000000 -> 31.258828 | D7: ='Assumption Sheet'!$B$95*'Assumption Sheet'!$B$96*'Project Income Statement'!D4*'Project Income Statement'!D5/10000000 -> 32.902811 | E7: ='Assumption Sheet'!$B$95*'Assumption Sheet'!$B$96*'Project Income Statement'!E4*'Project Income Statement'!E5/10000000 -> 34.58908 | F7: ='Assumption Sheet'!$B$95*'Assumption Sheet'!$B$96*'Project Income Statement'!F4*'Project Income Statement'!F5/10000000 -> 36.318534 | G7: ='Assumption Sheet'!$B$95*'Assumption Sheet'!$B$96*'Project Income Statement'!G4*'Project Income Statement'!G5/10000000 -> 38.092089 | H7: ='Assumption Sheet'!$B$95*'Assumption Sheet'!$B$96*'Project Income Statement'!H4*'Project Income Statement'!H5/10000000 -> 39.910679 | I7: ='Assumption Sheet'!$B$95*'Assumption Sheet'!$B$96*'Project Income Statement'!I4*'Project Income Statement'!I5/10000000 -> 40.509339 | ... K7: ='Assumption Sheet'!$B$95*'Assumption Sheet'!$B$96*'Project Income Statement'!K4*'Project Income Statement'!K5/10000000 -> 41.733734
A8: Food & Beverages | B8: =B7*'Assumption Sheet'!$B$91/'Assumption Sheet'!$B$90 -> 16.176136 | C8: =C7*'Assumption Sheet'!$B$91/'Assumption Sheet'!$B$90 -> 17.05027 | D8: =D7*'Assumption Sheet'!$B$91/'Assumption Sheet'!$B$90 -> 17.946988 | E8: =E7*'Assumption Sheet'!$B$91/'Assumption Sheet'!$B$90 -> 18.866771 | F8: =F7*'Assumption Sheet'!$B$91/'Assumption Sheet'!$B$90 -> 19.810109 | G8: =G7*'Assumption Sheet'!$B$91/'Assumption Sheet'!$B$90 -> 20.777503 | H8: =H7*'Assumption Sheet'!$B$91/'Assumption Sheet'!$B$90 -> 21.769461 | I8: =I7*'Assumption Sheet'!$B$91/'Assumption Sheet'!$B$90 -> 22.096003 | ... K8: =K7*'Assumption Sheet'!$B$91/'Assumption Sheet'!$B$90 -> 22.763855
A9: Other Sources | B9: =B7*'Assumption Sheet'!$B$92/'Assumption Sheet'!$B$90 -> 8.0880682 | C9: =C7*'Assumption Sheet'!$B$92/'Assumption Sheet'!$B$90 -> 8.5251349 | D9: =D7*'Assumption Sheet'!$B$92/'Assumption Sheet'!$B$90 -> 8.9734939 | E9: =E7*'Assumption Sheet'!$B$92/'Assumption Sheet'!$B$90 -> 9.4333855 | F9: =F7*'Assumption Sheet'!$B$92/'Assumption Sheet'!$B$90 -> 9.9050547 | G9: =G7*'Assumption Sheet'!$B$92/'Assumption Sheet'!$B$90 -> 10.388752 | H9: =H7*'Assumption Sheet'!$B$92/'Assumption Sheet'!$B$90 -> 10.884731 | I9: =I7*'Assumption Sheet'!$B$92/'Assumption Sheet'!$B$90 -> 11.048002 | ... K9: =K7*'Assumption Sheet'!$B$92/'Assumption Sheet'!$B$90 -> 11.381927
A10: Total Revenues during the Year [A] | B10: =SUM(B7:B9) -> 53.920455 | C10: =SUM(C7:C9) -> 56.834233 | D10: =SUM(D7:D9) -> 59.823293 | E10: =SUM(E7:E9) -> 62.889236 | F10: =SUM(F7:F9) -> 66.033698 | G10: =SUM(G7:G9) -> 69.258344 | H10: =SUM(H7:H9) -> 72.564871 | I10: =SUM(I7:I9) -> 73.653344 | ... K10: =SUM(K7:K9) -> 75.879517
A11: Total Expenditure for the Year:
A12: Variable Expenses:
A13: Food & Beverages Consumables | B13: =B10*'Assumption Sheet'!$B$105 -> 4.0440341 | C13: =C10*'Assumption Sheet'!$B$105 -> 4.2625675 | D13: =D10*'Assumption Sheet'!$B$105 -> 4.4867469 | E13: =E10*'Assumption Sheet'!$B$105 -> 4.7166927 | F13: =F10*'Assumption Sheet'!$B$105 -> 4.9525274 | G13: =G10*'Assumption Sheet'!$B$105 -> 5.1943758 | H13: =H10*'Assumption Sheet'!$B$105 -> 5.4423653 | I13: =I10*'Assumption Sheet'!$B$105 -> 5.5240008 | ... K13: =K10*'Assumption Sheet'!$B$105 -> 5.6909637
A14: Employee Costs | B14: =B10*'Assumption Sheet'!$B$106 -> 10.784091 | C14: =C10*'Assumption Sheet'!$B$106 -> 11.366847 | D14: =D10*'Assumption Sheet'!$B$106 -> 11.964659 | E14: =E10*'Assumption Sheet'!$B$106 -> 12.577847 | F14: =F10*'Assumption Sheet'!$B$106 -> 13.20674 | G14: =G10*'Assumption Sheet'!$B$106 -> 13.851669 | H14: =H10*'Assumption Sheet'!$B$106 -> 14.512974 | I14: =I10*'Assumption Sheet'!$B$106 -> 14.730669 | ... K14: =K10*'Assumption Sheet'!$B$106 -> 15.175903
A15: Power & Fuel | B15: =B10*'Assumption Sheet'!$B$107 -> 3.2352273 | C15: =C10*'Assumption Sheet'!$B$107 -> 3.410054 | D15: =D10*'Assumption Sheet'!$B$107 -> 3.5893976 | E15: =E10*'Assumption Sheet'!$B$107 -> 3.7733542 | F15: =F10*'Assumption Sheet'!$B$107 -> 3.9620219 | G15: =G10*'Assumption Sheet'!$B$107 -> 4.1555006 | H15: =H10*'Assumption Sheet'!$B$107 -> 4.3538923 | I15: =I10*'Assumption Sheet'!$B$107 -> 4.4192007 | ... K15: =K10*'Assumption Sheet'!$B$107 -> 4.552771
A16: Other Variable Expenses | B16: =B10*'Assumption Sheet'!$B$108 -> 2.1568182 | C16: =C10*'Assumption Sheet'!$B$108 -> 2.2733693 | D16: =D10*'Assumption Sheet'!$B$108 -> 2.3929317 | E16: =E10*'Assumption Sheet'!$B$108 -> 2.5155695 | F16: =F10*'Assumption Sheet'!$B$108 -> 2.6413479 | G16: =G10*'Assumption Sheet'!$B$108 -> 2.7703338 | H16: =H10*'Assumption Sheet'!$B$108 -> 2.9025948 | I16: =I10*'Assumption Sheet'!$B$108 -> 2.9461338 | ... K16: =K10*'Assumption Sheet'!$B$108 -> 3.0351807
A17: Service Fees to Mariott [Room revenue] | B17: =B7*'Assumption Sheet'!$B$109 -> 1.4828125 | C17: =C7*'Assumption Sheet'!$B$109 -> 1.5629414 | D17: =D7*'Assumption Sheet'!$B$109 -> 1.6451405 | E17: =E7*'Assumption Sheet'!$B$109 -> 1.729454 | F17: =F7*'Assumption Sheet'!$B$109 -> 1.8159267 | G17: =G7*'Assumption Sheet'!$B$109 -> 1.9046045 | H17: =H7*'Assumption Sheet'!$B$109 -> 1.995534 | I17: =I7*'Assumption Sheet'!$B$109 -> 2.025467 | ... K17: =K7*'Assumption Sheet'!$B$109 -> 2.0866867
A18: Total Variable Expenses [B] | B18: =SUM(B13:B17) -> 21.702983 | C18: =SUM(C13:C17) -> 22.875779 | D18: =SUM(D13:D17) -> 24.078875 | E18: =SUM(E13:E17) -> 25.312918 | F18: =SUM(F13:F17) -> 26.578564 | G18: =SUM(G13:G17) -> 27.876483 | H18: =SUM(H13:H17) -> 29.207361 | I18: =SUM(I13:I17) -> 29.645471 | ... K18: =SUM(K13:K17) -> 30.541505
A19: Fixed Expenses:
A20: Administrative & Selling Expenses | B20: =B10*'Assumption Sheet'!B112 -> 10.784091 | C20: =B20*(1+'Assumption Sheet'!$B$113) -> 11.8625 | D20: =C20*(1+'Assumption Sheet'!$B$113) -> 13.04875 | E20: =D20*(1+'Assumption Sheet'!$B$113) -> 14.353625 | F20: =E20*(1+'Assumption Sheet'!$B$113) -> 15.788988 | G20: =F20*(1+'Assumption Sheet'!$B$113) -> 17.367886 | H20: =G20*(1+'Assumption Sheet'!$B$113) -> 19.104675 | I20: =H20*(1+'Assumption Sheet'!$B$113) -> 21.015142 | J20: =I20*(1+'Assumption Sheet'!$B$113) -> 23.116657 | K20: =J20*(1+'Assumption Sheet'!$B$113) -> 25.428322
A21: Depreciation | B21: ='Assumption Sheet'!$C$87 -> 5.2514687 | C21: ='Assumption Sheet'!$C$87 -> 5.2514687 | D21: ='Assumption Sheet'!$C$87 -> 5.2514687 | E21: ='Assumption Sheet'!$C$87 -> 5.2514687 | F21: ='Assumption Sheet'!$C$87 -> 5.2514687 | G21: ='Assumption Sheet'!$C$87 -> 5.2514687 | H21: ='Assumption Sheet'!$C$87 -> 5.2514687 | I21: ='Assumption Sheet'!$C$87 -> 5.2514687 | ... K21: ='Assumption Sheet'!$C$87 -> 5.2514687
A22: Interest on Term Loan | B22: =B39 -> 6.961875 | C22: =C39 -> 6.6975 | D22: =D39 -> 6.256875 | E22: =E39 -> 5.64 | F22: =F39 -> 4.846875 | G22: =G39 -> 3.965625 | H22: =H39 -> 3.084375 | I22: =I39 -> 2.203125 | ... K22: =K39 -> 0.440625
A23: Total Fixed Expenses [C] | B23: =SUM(B20:B22) -> 22.997435 | C23: =SUM(C20:C22) -> 23.811469 | D23: =SUM(D20:D22) -> 24.557094 | E23: =SUM(E20:E22) -> 25.245094 | F23: =SUM(F20:F22) -> 25.887331 | G23: =SUM(G20:G22) -> 26.58498 | H23: =SUM(H20:H22) -> 27.440519 | I23: =SUM(I20:I22) -> 28.469736 | ... K23: =SUM(K20:K22) -> 31.120416
A24: Total Expenditure for the Year [D=B+C] | B24: =B23+B18 -> 44.700418 | C24: =C23+C18 -> 46.687248 | D24: =D23+D18 -> 48.635969 | E24: =E23+E18 -> 50.558011 | F24: =F23+F18 -> 52.465895 | G24: =G23+G18 -> 54.461463 | H24: =H23+H18 -> 56.647879 | I24: =I23+I18 -> 58.115207 | ... K24: =K23+K18 -> 61.661921
A25: Net Profit Before Tax [E=A-D] | B25: =B10-B24 -> 9.2200369 | C25: =C10-C24 -> 10.146985 | D25: =D10-D24 -> 11.187324 | E25: =E10-E24 -> 12.331225 | F25: =F10-F24 -> 13.567803 | G25: =G10-G24 -> 14.79688 | H25: =H10-H24 -> 15.916992 | I25: =I10-I24 -> 15.538137 | ... K25: =K10-K24 -> 14.217595
A26: [-] Tax | B26: =B25*'Assumption Sheet'!$B$115 -> 3.0426122 | C26: =C25*'Assumption Sheet'!$B$115 -> 3.3485052 | D26: =D25*'Assumption Sheet'!$B$115 -> 3.6918168 | E26: =E25*'Assumption Sheet'!$B$115 -> 4.0693042 | F26: =F25*'Assumption Sheet'!$B$115 -> 4.4773751 | G26: =G25*'Assumption Sheet'!$B$115 -> 4.8829705 | H26: =H25*'Assumption Sheet'!$B$115 -> 5.2526073 | I26: =I25*'Assumption Sheet'!$B$115 -> 5.1275852 | ... K26: =K25*'Assumption Sheet'!$B$115 -> 4.6918064
A27: Net Profit After Tax | B27: =B25-B26 -> 6.1774247 | C27: =C25-C26 -> 6.7984802 | D27: =D25-D26 -> 7.4955068 | E27: =E25-E26 -> 8.2619207 | F27: =F25-F26 -> 9.0904283 | G27: =G25-G26 -> 9.9139099 | H27: =H25-H26 -> 10.664385 | I27: =I25-I26 -> 10.410552 | ... K27: =K25-K26 -> 9.5257887
A31: Term Loan Repayment Schedule
A32: Particulars | B32: 2026-27 | C32: 2027-28 | D32: 2028-29 | E32: 2029-30 | F32: 2030-31 | G32: 2031-32 | H32: 2032-33 | I32: 2033-34 | J32: 2034-35 | K32: 2035-36
B33: All Amount in Rs. in Crores
A34: Repayment for the Year in %age | B34: 0.025 | C34: 0.05 | D34: 0.075 | E34: 0.1 | F34: 0.125 | G34: 0.125 | H34: 0.125 | I34: 0.125 | J34: 0.125 | K34: =1-SUM(B34:J34) -> 0.125
A35: Opening Balance | B35: ='Assumption Sheet'!E11 -> 70.5 | C35: =B37 -> 68.7375 | D35: =C37 -> 65.2125 | E35: =D37 -> 59.925 | F35: =E37 -> 52.875 | G35: =F37 -> 44.0625 | H35: =G37 -> 35.25 | I35: =H37 -> 26.4375 | J35: =I37 -> 17.625 | K35: =J37 -> 8.8125
A36: [-] Repayment | B36: =$B$35*B34 -> 1.7625 | C36: =$B$35*C34 -> 3.525 | D36: =$B$35*D34 -> 5.2875 | E36: =$B$35*E34 -> 7.05 | F36: =$B$35*F34 -> 8.8125 | G36: =$B$35*G34 -> 8.8125 | H36: =$B$35*H34 -> 8.8125 | I36: =$B$35*I34 -> 8.8125 | ... K36: =$B$35*K34 -> 8.8125
A37: Closing Balance | B37: =B35-B36 -> 68.7375 | C37: =C35-C36 -> 65.2125 | D37: =D35-D36 -> 59.925 | E37: =E35-E36 -> 52.875 | F37: =F35-F36 -> 44.0625 | G37: =G35-G36 -> 35.25 | H37: =H35-H36 -> 26.4375 | I37: =I35-I36 -> 17.625 | ... K37: =K35-K36 -> -1.4210855e-14
A38: Average Balance | B38: =(B35+B37)/2 -> 69.61875 | C38: =(C35+C37)/2 -> 66.975 | D38: =(D35+D37)/2 -> 62.56875 | E38: =(E35+E37)/2 -> 56.4 | F38: =(F35+F37)/2 -> 48.46875 | G38: =(G35+G37)/2 -> 39.65625 | H38: =(H35+H37)/2 -> 30.84375 | I38: =(I35+I37)/2 -> 22.03125 | ... K38: =(K35+K37)/2 -> 4.40625
A39: Interest on Term Loan | B39: =B38*'Assumption Sheet'!$B$75 -> 6.961875 | C39: =C38*'Assumption Sheet'!$B$75 -> 6.6975 | D39: =D38*'Assumption Sheet'!$B$75 -> 6.256875 | E39: =E38*'Assumption Sheet'!$B$75 -> 5.64 | F39: =F38*'Assumption Sheet'!$B$75 -> 4.846875 | G39: =G38*'Assumption Sheet'!$B$75 -> 3.965625 | H39: =H38*'Assumption Sheet'!$B$75 -> 3.084375 | I39: =I38*'Assumption Sheet'!$B$75 -> 2.203125 | ... K39: =K38*'Assumption Sheet'!$B$75 -> 0.440625
A41: Debt Service Coverage Ratio
A42: Particulars | B42: 2026-27 | C42: 2027-28 | D42: 2028-29 | E42: 2029-30 | F42: 2030-31 | G42: 2031-32 | H42: 2032-33 | I42: 2033-34 | J42: 2034-35 | K42: 2035-36
B43: All Amount in Rs. in Crores
A44: Net Profit After tax | B44: =B27 -> 6.1774247 | C44: =C27 -> 6.7984802 | D44: =D27 -> 7.4955068 | E44: =E27 -> 8.2619207 | F44: =F27 -> 9.0904283 | G44: =G27 -> 9.9139099 | H44: =H27 -> 10.664385 | I44: =I27 -> 10.410552 | ... K44: =K27 -> 9.5257887
A45: [+] Interest Payment During the Year | B45: =B22 -> 6.961875 | C45: =C22 -> 6.6975 | D45: =D22 -> 6.256875 | E45: =E22 -> 5.64 | F45: =F22 -> 4.846875 | G45: =G22 -> 3.965625 | H45: =H22 -> 3.084375 | I45: =I22 -> 2.203125 | ... K45: =K22 -> 0.440625
A46: [+] Depreciation for the year | B46: =B21 -> 5.2514687 | C46: =C21 -> 5.2514687 | D46: =D21 -> 5.2514687 | E46: =E21 -> 5.2514687 | F46: =F21 -> 5.2514687 | G46: =G21 -> 5.2514687 | H46: =H21 -> 5.2514687 | I46: =I21 -> 5.2514687 | ... K46: =K21 -> 5.2514687
A47: Total Cash-flow available for servicing the debt | B47: =SUM(B44:B46) -> 18.390768 | C47: =SUM(C44:C46) -> 18.747449 | D47: =SUM(D44:D46) -> 19.003851 | E47: =SUM(E44:E46) -> 19.153389 | F47: =SUM(F44:F46) -> 19.188772 | G47: =SUM(G44:G46) -> 19.131004 | H47: =SUM(H44:H46) -> 19.000228 | I47: =SUM(I44:I46) -> 17.865146 | ... K47: =SUM(K44:K46) -> 15.217882
A48: Interest Payment During the Year | B48: =B45 -> 6.961875 | C48: =C45 -> 6.6975 | D48: =D45 -> 6.256875 | E48: =E45 -> 5.64 | F48: =F45 -> 4.846875 | G48: =G45 -> 3.965625 | H48: =H45 -> 3.084375 | I48: =I45 -> 2.203125 | ... K48: =K45 -> 0.440625
A49: [+] Principal Repayment during the year | B49: =B36 -> 1.7625 | C49: =C36 -> 3.525 | D49: =D36 -> 5.2875 | E49: =E36 -> 7.05 | F49: =F36 -> 8.8125 | G49: =G36 -> 8.8125 | H49: =H36 -> 8.8125 | I49: =I36 -> 8.8125 | ... K49: =K36 -> 8.8125
A50: Total Debt repayment during the Year | B50: =SUM(B48:B49) -> 8.724375 | C50: =SUM(C48:C49) -> 10.2225 | D50: =SUM(D48:D49) -> 11.544375 | E50: =SUM(E48:E49) -> 12.69 | F50: =SUM(F48:F49) -> 13.659375 | G50: =SUM(G48:G49) -> 12.778125 | H50: =SUM(H48:H49) -> 11.896875 | I50: =SUM(I48:I49) -> 11.015625 | ... K50: =SUM(K48:K49) -> 9.253125
A51: Debt Service Coverage Ratio [in times] | B51: =B47/B50 -> 2.1079755 | C51: =C47/C50 -> 1.8339397 | D51: =D47/D50 -> 1.6461567 | E51: =E47/E50 -> 1.5093294 | F51: =F47/F50 -> 1.404806 | G51: =G47/G50 -> 1.4971683 | H51: =H47/H50 -> 1.5970772 | I51: =I47/I50 -> 1.6218004 | ... K51: =K47/K50 -> 1.6446209
A52: Average DSCR [in times] | B52: =SUM(B47:K47)/SUM(B50:K50) -> 1.6289235
A55: Internal Rate of Return
A56: Particulars | B56: 2024-25 | C56: 2025-26 | D56: 2026-27 | E56: 2027-28 | F56: 2028-29 | G56: 2029-30 | H56: 2030-31 | I56: 2031-32 | J56: 2032-33 | K56: 2033-34 | L56: 2034-35 | M56: 2035-36
B57: All Amounts in Rs. in Crores
A58: Cash-Flow After Tax | B58: 0 | C58: 0 | D58: =B47 -> 18.390768 | E58: =C47 -> 18.747449 | F58: =D47 -> 19.003851 | G58: =E47 -> 19.153389 | H58: =F47 -> 19.188772 | I58: =G47 -> 19.131004 | J58: =H47 -> 19.000228 | K58: =I47 -> 17.865146 | ... M58: =K47 -> 15.217882
A59: [+] Terminal Value of Fixed Assets | B59: 0 | C59: 0 | D59: 0 | E59: 0 | F59: 0 | G59: 0 | H59: 0 | I59: 0 | J59: 0 | K59: 0 | L59: 0 | M59: ='Assumption Sheet'!B11-SUM('Project Income Statement'!B21:K21) -> 82.062812
A60: Project Cash Outflow | B60: =-'Assumption Sheet'!B121 -> -78.004375 | C60: =-'Assumption Sheet'!C121 -> -56.573125 | D60: 0 | E60: 0 | F60: 0 | G60: 0 | H60: 0 | I60: 0 | J60: 0 | K60: 0 | L60: 0 | M60: 0
A61: Total Cash-Flows | B61: =SUM(B58:B60) -> -78.004375 | C61: =SUM(C58:C60) -> -56.573125 | D61: =SUM(D58:D60) -> 18.390768 | E61: =SUM(E58:E60) -> 18.747449 | F61: =SUM(F58:F60) -> 19.003851 | G61: =SUM(G58:G60) -> 19.153389 | H61: =SUM(H58:H60) -> 19.188772 | I61: =SUM(I58:I60) -> 19.131004 | ... M61: =SUM(M58:M60) -> 97.280695
A62: Internal Rate of Return | B62: =IRR(B61:M61) -> 0.10305145
A64: Pay-Back Period
A65: Particulars | B65: 2026-27 | C65: 2027-28 | D65: 2028-29 | E65: 2029-30 | F65: 2030-31 | G65: 2031-32 | H65: 2032-33 | I65: 2033-34 | J65: 2034-35 | K65: 2035-36
B66: All Amount in Rs. in Crores
A67: Total Cash-flow available for servicing the debt | B67: =B47 -> 18.390768 | C67: =C47 -> 18.747449 | D67: =D47 -> 19.003851 | E67: =E47 -> 19.153389 | F67: =F47 -> 19.188772 | G67: =G47 -> 19.131004 | H67: =H47 -> 19.000228 | I67: =I47 -> 17.865146 | ... K67: =K47 -> 15.217882
A68: Average Cash-Flows | B68: =AVERAGE(B67:K67) -> 18.230709
A69: Cost of Project | B69: ='Assumption Sheet'!D121 -> 134.5775
A70: Simple Pay-Back Period | B70: =B69/B68 -> 7.3819127
A72: Break-Even Point
A73: Particulars | B73: 2026-27 | C73: 2027-28 | D73: 2028-29 | E73: 2029-30 | F73: 2030-31 | G73: 2031-32 | H73: 2032-33 | I73: 2033-34 | J73: 2034-35 | K73: 2035-36
B74: All Amount in Rs. in Crores
A75: Total Sales [A] | B75: =B10 -> 53.920455 | C75: =C10 -> 56.834233 | D75: =D10 -> 59.823293 | E75: =E10 -> 62.889236 | F75: =F10 -> 66.033698 | G75: =G10 -> 69.258344 | H75: =H10 -> 72.564871 | I75: =I10 -> 73.653344 | ... K75: =K10 -> 75.879517
A76: [-] Variable Cost [B] | B76: =B18 -> 21.702983 | C76: =C18 -> 22.875779 | D76: =D18 -> 24.078875 | E76: =E18 -> 25.312918 | F76: =F18 -> 26.578564 | G76: =G18 -> 27.876483 | H76: =H18 -> 29.207361 | I76: =I18 -> 29.645471 | ... K76: =K18 -> 30.541505
A77: Contribution [C=A-B] | B77: =B75-B76 -> 32.217472 | C77: =C75-C76 -> 33.958454 | D77: =D75-D76 -> 35.744417 | E77: =E75-E76 -> 37.576319 | F77: =F75-F76 -> 39.455135 | G77: =G75-G76 -> 41.38186 | H77: =H75-H76 -> 43.357511 | I77: =I75-I76 -> 44.007873 | ... K77: =K75-K76 -> 45.338011
A78: Profit Volume Ratio [D=C/A] | B78: =B77/B75 -> 0.5975 | C78: =C77/C75 -> 0.5975 | D78: =D77/D75 -> 0.5975 | E78: =E77/E75 -> 0.5975 | F78: =F77/F75 -> 0.5975 | G78: =G77/G75 -> 0.5975 | H78: =H77/H75 -> 0.5975 | I78: =I77/I75 -> 0.5975 | ... K78: =K77/K75 -> 0.5975
A79: Fixed Costs [E] | B79: =B23 -> 22.997435 | C79: =C23 -> 23.811469 | D79: =D23 -> 24.557094 | E79: =E23 -> 25.245094 | F79: =F23 -> 25.887331 | G79: =G23 -> 26.58498 | H79: =H23 -> 27.440519 | I79: =I23 -> 28.469736 | ... K79: =K23 -> 31.120416
A80: Net Profit Before Tax [F=C-E] | B80: =B77-B79 -> 9.2200369 | C80: =C77-C79 -> 10.146985 | D80: =D77-D79 -> 11.187324 | E80: =E77-E79 -> 12.331225 | F80: =F77-F79 -> 13.567803 | G80: =G77-G79 -> 14.79688 | H80: =H77-H79 -> 15.916992 | I80: =I77-I79 -> 15.538137 | ... K80: =K77-K79 -> 14.217595
A81: Break-Even Point [E/D] | B81: =B79/B78 -> 38.48943 | C81: =C79/C78 -> 39.851831 | D81: =D79/D78 -> 41.099738 | E81: =E79/E78 -> 42.251203 | F81: =F79/F78 -> 43.326077 | G81: =G79/G78 -> 44.49369 | H81: =H79/H78 -> 45.925554 | I81: =I79/I78 -> 47.648094 | ... K81: =K79/K78 -> 52.084378
A82: BEP as a %age of Sales | B82: =B81/B75 -> 0.71381873 | C82: =C81/C75 -> 0.70119413 | D82: =D81/D75 -> 0.687019 | E82: =E81/E75 -> 0.6718352 | F82: =F81/F75 -> 0.65612072 | G82: =G81/G75 -> 0.64243076 | H82: =H81/H75 -> 0.63288963 | I82: =I81/I75 -> 0.6469237 | ... K82: =K81/K75 -> 0.68640894
A83: Fixed Costs excluding Depreciation | B83: =B23-B21 -> 17.745966 | C83: =C23-C21 -> 18.56 | D83: =D23-D21 -> 19.305625 | E83: =E23-E21 -> 19.993625 | F83: =F23-F21 -> 20.635863 | G83: =G23-G21 -> 21.333511 | H83: =H23-H21 -> 22.18905 | I83: =I23-I21 -> 23.218267 | ... K83: =K23-K21 -> 25.868947
A84: Cash-Break Even Point | B84: =B83/B78 -> 29.700361 | C84: =C83/C78 -> 31.062762 | D84: =D83/D78 -> 32.310669 | E84: =E83/E78 -> 33.462134 | F84: =F83/F78 -> 34.537008 | G84: =G83/G78 -> 35.704621 | H84: =H83/H78 -> 37.136485 | I84: =I83/I78 -> 38.859025 | ... K84: =K83/K78 -> 43.295309
A85: Cash Break Even Point as %age of sales | B85: =B84/B75 -> 0.55081808 | C85: =C84/C75 -> 0.5465502 | D85: =D84/D75 -> 0.54010182 | E85: =E84/E75 -> 0.53208046 | F85: =F84/F75 -> 0.52302096 | G85: =G84/G75 -> 0.51552809 | H85: =H84/H75 -> 0.51176946 | I85: =I84/I75 -> 0.52759349 | ... K85: =K84/K75 -> 0.57057967

Sheet Projected Balance Sheet
A2: Particulars | B2: 2024-25 | C2: 2025-26 | D2: 2026-27 | E2: 2027-28 | F2: 2028-29 | G2: 2029-30 | H2: 2030-31 | I2: 2031-32 | J2: 2032-33 | K2: 2033-34 | L2: 2034-35 | M2: 2035-36
B3: All Amounts in Rs. in Crores
A4: Assets:
A5: Gross Block | B5: 0 | C5: 0 | D5: ='Assumption Sheet'!D121 -> 134.5775 | E5: =D5 -> 134.5775 | F5: =E5 -> 134.5775 | G5: =F5 -> 134.5775 | H5: =G5 -> 134.5775 | I5: =H5 -> 134.5775 | J5: =I5 -> 134.5775 | K5: =J5 -> 134.5775 | L5: =K5 -> 134.5775 | M5: =L5 -> 134.5775
A6: [-] Accumulated Depreciation | B6: 0 | C6: 0 | D6: ='Project Income Statement'!B21 -> 5.2514687 | E6: =D6+'Project Income Statement'!C21 -> 10.502937 | F6: =E6+'Project Income Statement'!D21 -> 15.754406 | G6: =F6+'Project Income Statement'!E21 -> 21.005875 | H6: =G6+'Project Income Statement'!F21 -> 26.257344 | I6: =H6+'Project Income Statement'!G21 -> 31.508813 | J6: =I6+'Project Income Statement'!H21 -> 36.760281 | K6: =J6+'Project Income Statement'!I21 -> 42.01175 | L6: =K6+'Project Income Statement'!J21 -> 47.263219 | M6: =L6+'Project Income Statement'!K21 -> 52.514688
A7: Net Block | B7: =B5-B6 -> 0 | C7: =C5-C6 -> 0 | D7: =D5-D6 -> 129.32603 | E7: =E5-E6 -> 124.07456 | F7: =F5-F6 -> 118.82309 | G7: =G5-G6 -> 113.57162 | H7: =H5-H6 -> 108.32016 | I7: =I5-I6 -> 103.06869 | ... M7: =M5-M6 -> 82.062812
A8: Capital Work in Progress | B8: ='Assumption Sheet'!B121 -> 78.004375 | C8: =B8+'Assumption Sheet'!C121 -> 134.5775 | D8: 0 | E8: 0 | F8: 0 | G8: 0 | H8: 0 | I8: 0 | J8: 0 | K8: 0 | L8: 0 | M8: 0
A9: Cash & Bank Balance | B9: ='Projected Cash FLow Statement'!B16 -> 0 | C9: ='Projected Cash FLow Statement'!C16 -> 0 | D9: ='Projected Cash FLow Statement'!D16 -> 9.6663935 | E9: ='Projected Cash FLow Statement'!E16 -> 18.191342 | F9: ='Projected Cash FLow Statement'!F16 -> 25.650818 | G9: ='Projected Cash FLow Statement'!G16 -> 32.114208 | H9: ='Projected Cash FLow Statement'!H16 -> 37.643605 | I9: ='Projected Cash FLow Statement'!I16 -> 43.996483 | ... M9: ='Projected Cash FLow Statement'!M16 -> 70.388337
A10: Total Assets | B10: =SUM(B7:B9) -> 78.004375 | C10: =SUM(C7:C9) -> 134.5775 | D10: =SUM(D7:D9) -> 138.99242 | E10: =SUM(E7:E9) -> 142.2659 | F10: =SUM(F7:F9) -> 144.47391 | G10: =SUM(G7:G9) -> 145.68583 | H10: =SUM(H7:H9) -> 145.96376 | I10: =SUM(I7:I9) -> 147.06517 | ... M10: =SUM(M7:M9) -> 152.45115
A11: Core Equity Capital | B11: =SUM('Assumption Sheet'!B63:E63)+SUM('Assumption Sheet'!B73:E73) -> 39.654375 | C11: =SUM('Assumption Sheet'!F63:I63)+SUM('Assumption Sheet'!F73:I73)+B11 -> 64.0775 | D11: =C11 -> 64.0775 | E11: =D11 -> 64.0775 | F11: =E11 -> 64.0775 | G11: =F11 -> 64.0775 | H11: =G11 -> 64.0775 | I11: =H11 -> 64.0775 | J11: =I11 -> 64.0775 | K11: =J11 -> 64.0775 | ... M11: =L11 -> 64.0775
A12: [+] Reserves & Surplus | B12: 0 | C12: 0 | D12: ='Project Income Statement'!B27 -> 6.1774247 | E12: =D12+'Project Income Statement'!C27 -> 12.975905 | F12: =E12+'Project Income Statement'!D27 -> 20.471412 | G12: =F12+'Project Income Statement'!E27 -> 28.733333 | H12: =G12+'Project Income Statement'!F27 -> 37.823761 | I12: =H12+'Project Income Statement'!G27 -> 47.737671 | J12: =I12+'Project Income Statement'!H27 -> 58.402055 | K12: =J12+'Project Income Statement'!I27 -> 68.812607 | L12: =K12+'Project Income Statement'!J27 -> 78.847861 | M12: =L12+'Project Income Statement'!K27 -> 88.37365
A13: Net Worth | B13: =SUM(B11:B12) -> 39.654375 | C13: =SUM(C11:C12) -> 64.0775 | D13: =SUM(D11:D12) -> 70.254925 | E13: =SUM(E11:E12) -> 77.053405 | F13: =SUM(F11:F12) -> 84.548912 | G13: =SUM(G11:G12) -> 92.810833 | H13: =SUM(H11:H12) -> 101.90126 | I13: =SUM(I11:I12) -> 111.81517 | ... M13: =SUM(M11:M12) -> 152.45115
A14: Bank Loan | B14: =SUM('Assumption Sheet'!B64:E64) -> 38.35 | C14: =SUM('Assumption Sheet'!F64:I64)+B14 -> 70.5 | D14: ='Project Income Statement'!B37 -> 68.7375 | E14: ='Project Income Statement'!C37 -> 65.2125 | F14: ='Project Income Statement'!D37 -> 59.925 | G14: ='Project Income Statement'!E37 -> 52.875 | H14: ='Project Income Statement'!F37 -> 44.0625 | I14: ='Project Income Statement'!G37 -> 35.25 | J14: ='Project Income Statement'!H37 -> 26.4375 | K14: ='Project Income Statement'!I37 -> 17.625 | ... M14: ='Project Income Statement'!K37 -> -1.4210855e-14
A15: Total Liabilities | B15: =SUM(B13:B14) -> 78.004375 | C15: =SUM(C13:C14) -> 134.5775 | D15: =SUM(D13:D14) -> 138.99242 | E15: =SUM(E13:E14) -> 142.2659 | F15: =SUM(F13:F14) -> 144.47391 | G15: =SUM(G13:G14) -> 145.68583 | H15: =SUM(H13:H14) -> 145.96376 | I15: =SUM(I13:I14) -> 147.06517 | ... M15: =SUM(M13:M14) -> 152.45115
A16: Difference | B16: =B15-B10 -> 0 | C16: =C15-C10 -> 0 | D16: =D15-D10 -> 0 | E16: =E15-E10 -> 0 | F16: =F15-F10 -> 0 | G16: =G15-G10 -> 0 | H16: =H15-H10 -> 0 | I16: =I15-I10 -> 0 | ... M16: =M15-M10 -> 0

Sheet Projected Cash FLow Statement
A2: Particulars | B2: 2024-25 | C2: 2025-26 | D2: 2026-27 | E2: 2027-28 | F2: 2028-29 | G2: 2029-30 | H2: 2030-31 | I2: 2031-32 | J2: 2032-33 | K2: 2033-34 | L2: 2034-35 | M2: 2035-36
B3: All Amounts in Rs. in Crores
A4: Sources of Finance:
A5: Net Profit After Tax | B5: 0 | C5: 0 | D5: ='Project Income Statement'!B27 -> 6.1774247 | E5: ='Project Income Statement'!C27 -> 6.7984802 | F5: ='Project Income Statement'!D27 -> 7.4955068 | G5: ='Project Income Statement'!E27 -> 8.2619207 | H5: ='Project Income Statement'!F27 -> 9.0904283 | I5: ='Project Income Statement'!G27 -> 9.9139099 | J5: ='Project Income Statement'!H27 -> 10.664385 | K5: ='Project Income Statement'!I27 -> 10.410552 | ... M5: ='Project Income Statement'!K27 -> 9.5257887
A6: [+] Depreciation | B6: 0 | C6: 0 | D6: ='Project Income Statement'!B21 -> 5.2514687 | E6: ='Project Income Statement'!C21 -> 5.2514687 | F6: ='Project Income Statement'!D21 -> 5.2514687 | G6: ='Project Income Statement'!E21 -> 5.2514687 | H6: ='Project Income Statement'!F21 -> 5.2514687 | I6: ='Project Income Statement'!G21 -> 5.2514687 | J6: ='Project Income Statement'!H21 -> 5.2514687 | K6: ='Project Income Statement'!I21 -> 5.2514687 | ... M6: ='Project Income Statement'!K21 -> 5.2514687
A7: [+] Capital Infusion | B7: ='Projected Balance Sheet'!B11 -> 39.654375 | C7: ='Projected Balance Sheet'!C11-'Projected Balance Sheet'!B11 -> 24.423125 | D7: 0 | E7: 0 | F7: 0 | G7: 0 | H7: 0 | I7: 0 | J7: 0 | K7: 0 | L7: 0 | M7: 0
A8: [+] Debt Capital Raised | B8: ='Projected Balance Sheet'!B14 -> 38.35 | C8: ='Projected Balance Sheet'!C14-'Projected Balance Sheet'!B14 -> 32.15
A9: Total Funds Infused [A] | B9: =SUM(B5:B8) -> 78.004375 | C9: =SUM(C5:C8) -> 56.573125 | D9: =SUM(D5:D8) -> 11.428893 | E9: =SUM(E5:E8) -> 12.049949 | F9: =SUM(F5:F8) -> 12.746976 | G9: =SUM(G5:G8) -> 13.513389 | H9: =SUM(H5:H8) -> 14.341897 | I9: =SUM(I5:I8) -> 15.165379 | ... M9: =SUM(M5:M8) -> 14.777257
A10: Use of Funds:
A11: Fixed Assets Purchased | B11: =SUM('Assumption Sheet'!B65:E65)+SUM('Assumption Sheet'!B73:E73) -> 78.004375 | C11: =SUM('Assumption Sheet'!F65:I65)+SUM('Assumption Sheet'!F73:I73) -> 56.573125 | D11: 0 | E11: 0 | F11: 0 | G11: 0 | H11: 0 | I11: 0 | J11: 0 | K11: 0 | L11: 0 | M11: 0
A12: Term Loan Repaid | B12: 0 | C12: 0 | D12: ='Project Income Statement'!B36 -> 1.7625 | E12: ='Project Income Statement'!C36 -> 3.525 | F12: ='Project Income Statement'!D36 -> 5.2875 | G12: ='Project Income Statement'!E36 -> 7.05 | H12: ='Project Income Statement'!F36 -> 8.8125 | I12: ='Project Income Statement'!G36 -> 8.8125 | J12: ='Project Income Statement'!H36 -> 8.8125 | K12: ='Project Income Statement'!I36 -> 8.8125 | ... M12: ='Project Income Statement'!K36 -> 8.8125
A13: Total Out-Flow [B] | B13: =SUM(B11:B12) -> 78.004375 | C13: =SUM(C11:C12) -> 56.573125 | D13: =SUM(D11:D12) -> 1.7625 | E13: =SUM(E11:E12) -> 3.525 | F13: =SUM(F11:F12) -> 5.2875 | G13: =SUM(G11:G12) -> 7.05 | H13: =SUM(H11:H12) -> 8.8125 | I13: =SUM(I11:I12) -> 8.8125 | ... M13: =SUM(M11:M12) -> 8.8125
A14: Surplus [A-B] | B14: =B9-B13 -> 0 | C14: =C9-C13 -> 0 | D14: =D9-D13 -> 9.6663935 | E14: =E9-E13 -> 8.524949 | F14: =F9-F13 -> 7.4594756 | G14: =G9-G13 -> 6.4633895 | H14: =H9-H13 -> 5.529397 | I14: =I9-I13 -> 6.3528786 | ... M14: =M9-M13 -> 5.9647575
A15: Opening Balance | B15: 0 | C15: =B16 -> 0 | D15: =C16 -> 0 | E15: =D16 -> 9.6663935 | F15: =E16 -> 18.191342 | G15: =F16 -> 25.650818 | H15: =G16 -> 32.114208 | I15: =H16 -> 37.643605 | J15: =I16 -> 43.996483 | ... M15: =L16 -> 64.42358
A16: Closing Balance | B16: =SUM(B14:B15) -> 0 | C16: =SUM(C14:C15) -> 0 | D16: =SUM(D14:D15) -> 9.6663935 | E16: =SUM(E14:E15) -> 18.191342 | F16: =SUM(F14:F15) -> 25.650818 | G16: =SUM(G14:G15) -> 32.114208 | H16: =SUM(H14:H15) -> 37.643605 | I16: =SUM(I14:I15) -> 43.996483 | ... M16: =SUM(M14:M15) -> 70.388337
